LICENSE
MANIFEST.in
README.rst
setup.cfg
setup.py
versioneer.py
catalyst/__init__.py
catalyst/__main__.py
catalyst/_protocol.pyx
catalyst/_version.py
catalyst/algorithm.py
catalyst/api.py
catalyst/api.pyi
catalyst/catalyst_warnings.py
catalyst/constants.py
catalyst/dispatch.py
catalyst/errors.py
catalyst/protocol.py
catalyst/test_algorithms.py
catalyst/assets/__init__.py
catalyst/assets/_assets.pyx
catalyst/assets/asset_db_migrations.py
catalyst/assets/asset_db_schema.py
catalyst/assets/asset_writer.py
catalyst/assets/assets.py
catalyst/assets/continuous_futures.pyx
catalyst/assets/futures.py
catalyst/assets/roll_finder.py
catalyst/assets/synthetic.py
catalyst/curate/__init__.py
catalyst/curate/poloniex.py
catalyst/data/__init__.py
catalyst/data/_adjustments.pyx
catalyst/data/_equities.pyx
catalyst/data/_minute_bar_internal.pyx
catalyst/data/_resample.pyx
catalyst/data/bar_reader.py
catalyst/data/benchmarks.py
catalyst/data/continuous_future_reader.py
catalyst/data/data_portal.py
catalyst/data/dispatch_bar_reader.py
catalyst/data/history_loader.py
catalyst/data/loader.py
catalyst/data/minute_bars.py
catalyst/data/resample.py
catalyst/data/session_bars.py
catalyst/data/treasuries.py
catalyst/data/treasuries_can.py
catalyst/data/us_equity_pricing.py
catalyst/data/bundles/__init__.py
catalyst/data/bundles/base.py
catalyst/data/bundles/base_pricing.py
catalyst/data/bundles/core.py
catalyst/data/bundles/poloniex.py
catalyst/data/bundles/quandl.py
catalyst/data/bundles/yahoo.py
catalyst/examples/__init__.py
catalyst/examples/arbitrage_with_interface.py
catalyst/examples/buy_and_hodl.py
catalyst/examples/buy_btc_simple.py
catalyst/examples/buy_btc_simple_wip.py
catalyst/examples/buy_low_sell_high.py
catalyst/examples/buy_low_sell_high_wip.py
catalyst/examples/dual_moving_average.py
catalyst/examples/mean_reversion_simple.py
catalyst/examples/mean_reversion_simple_custom_fees.py
catalyst/examples/portfolio_optimization.py
catalyst/examples/rsi_profit_target.py
enigma_catalyst.egg-info/PKG-INFO
enigma_catalyst.egg-info/SOURCES.txt
enigma_catalyst.egg-info/dependency_links.txt
enigma_catalyst.egg-info/entry_points.txt
enigma_catalyst.egg-info/requires.txt
enigma_catalyst.egg-info/top_level.txt
